{
  "id": "progress_33879",
  "userId": "patient_7253",
  "planId": "plan_18308",
  "date": "2024-09-11T13:59:38.703984",
  "exerciseLogs": [
    {
      "exerciseId": "ex_neck_1_4357",
      "exerciseName": "Neck Exercise 6",
      "setsCompleted": 2,
      "repsCompleted": 6,
      "durationSeconds": 55,
      "painLevel": 5,
      "notes": "Need to modify"
    },
    {
      "exerciseId": "ex_neck_2_5320",
      "exerciseName": "Neck Exercise 1",
      "setsCompleted": 2,
      "repsCompleted": 8,
      "durationSeconds": 35,
      "painLevel": 4,
      "notes": "Too challenging"
    },
    {
      "exerciseId": "ex_neck_3_7961",
      "exerciseName": "Neck Exercise 4",
      "setsCompleted": 3,
      "repsCompleted": 8,
      "durationSeconds": 69,
      "painLevel": 9,
      "notes": "Felt good"
    },
    {
      "exerciseId": "ex_neck_4_4087",
      "exerciseName": "Neck Exercise 3",
      "setsCompleted": 1,
      "repsCompleted": 11,
      "durationSeconds": 51,
      "painLevel": 1,
      "notes": null
    }
  ],
  "metrics": {
    "neck_rom": 178,
    "neck_strength": 9
  },
  "feedback": "Still experiencing pain during certain movements",
  "overallRating": 4,
  "adherencePercentage": 88
}