{
  "id": "progress_72471",
  "userId": "patient_3107",
  "planId": "plan_21296",
  "date": "2024-12-24T13:59:38.683934",
  "exerciseLogs": [
    {
      "exerciseId": "ex_wrist_1_1045",
      "exerciseName": "Wrist Exercise 3",
      "setsCompleted": 2,
      "repsCompleted": 7,
      "durationSeconds": 80,
      "painLevel": 2,
      "notes": "Getting easier"
    },
    {
      "exerciseId": "ex_wrist_3_3990",
      "exerciseName": "Wrist Exercise 1",
      "setsCompleted": 2,
      "repsCompleted": 1,
      "durationSeconds": 64,
      "painLevel": 1,
      "notes": null
    },
    {
      "exerciseId": "ex_wrist_4_9911",
      "exerciseName": "Wrist Exercise 5",
      "setsCompleted": 1,
      "repsCompleted": 9,
      "durationSeconds": 63,
      "painLevel": 10,
      "notes": "Getting easier"
    },
    {
      "exerciseId": "ex_wrist_5_5732",
      "exerciseName": "Wrist Exercise 4",
      "setsCompleted": 3,
      "repsCompleted": 3,
      "durationSeconds": 57,
      "painLevel": 10,
      "notes": "Need to modify"
    }
  ],
  "metrics": {
    "wrist_rom": 75,
    "wrist_strength": 3
  },
  "feedback": "Still experiencing pain during certain movements",
  "overallRating": 2,
  "adherencePercentage": 53
}