{
  "id": "progress_50940",
  "userId": "patient_7662",
  "planId": "plan_18040",
  "date": "2025-03-12T13:59:38.678933",
  "exerciseLogs": [
    {
      "exerciseId": "ex_elbow_1_5226",
      "exerciseName": "Elbow Exercise 1",
      "setsCompleted": 4,
      "repsCompleted": 11,
      "durationSeconds": 73,
      "painLevel": 9,
      "notes": "Getting easier"
    },
    {
      "exerciseId": "ex_elbow_2_7573",
      "exerciseName": "Elbow Exercise 5",
      "setsCompleted": 2,
      "repsCompleted": 8,
      "durationSeconds": 88,
      "painLevel": 6,
      "notes": "Felt good"
    },
    {
      "exerciseId": "ex_elbow_3_2717",
      "exerciseName": "Elbow Exercise 6",
      "setsCompleted": 2,
      "repsCompleted": 8,
      "durationSeconds": 81,
      "painLevel": 2,
      "notes": "Need to modify"
    },
    {
      "exerciseId": "ex_elbow_4_7213",
      "exerciseName": "Elbow Exercise 4",
      "setsCompleted": 2,
      "repsCompleted": 8,
      "durationSeconds": 85,
      "painLevel": 5,
      "notes": null
    },
    {
      "exerciseId": "ex_elbow_5_6324",
      "exerciseName": "Elbow Exercise 2",
      "setsCompleted": 2,
      "repsCompleted": 12,
      "durationSeconds": 85,
      "painLevel": 1,
      "notes": "Getting easier"
    }
  ],
  "metrics": {
    "elbow_rom": 81,
    "elbow_strength": 9
  },
  "feedback": null,
  "overallRating": 3,
  "adherencePercentage": 92
}